<?xml version="1.0" encoding="utf-8"?>
<!DOCTYPE hibernate-mapping PUBLIC "-//Hibernate/Hibernate Mapping DTD 3.0//EN"
"http://hibernate.sourceforge.net/hibernate-mapping-3.0.dtd">
<!-- 
    Mapping file autogenerated by MyEclipse Persistence Tools
-->
<hibernate-mapping>
    <class name="com.museum.domain.Advice" table="advice" catalog="mymuseum">
        <id name="adviceId" type="java.lang.Integer">
            <column name="Advice_id" />
            <generator class="native" />
        </id>
        <property name="adviceState" type="java.lang.String">
            <column name="Advice_state" length="40" not-null="true" />
        </property>
        <property name="commentId" type="java.lang.Integer">
            <column name="Comment_id" not-null="true" />
        </property>
        <property name="replyId" type="java.lang.Integer">
            <column name="Reply_id" not-null="false" />
        </property>
        <property name="adviceCheckState" type="java.lang.String">
            <column name="Advice_check_state" length="40" not-null="true" />
        </property>
    </class>
</hibernate-mapping>
